setup.py
cmc_dataeng_internship_kenneth_paulsen/exercise13.py
cmc_dataeng_internship_kenneth_paulsen.egg-info/PKG-INFO
cmc_dataeng_internship_kenneth_paulsen.egg-info/SOURCES.txt
cmc_dataeng_internship_kenneth_paulsen.egg-info/dependency_links.txt
cmc_dataeng_internship_kenneth_paulsen.egg-info/top_level.txt